{
  "footTraffic": [
    {"locationId": "loc_downtown_high_street",   "date": "2026-05-12", "hour": "12", "peakHours": ["12","13","18","19"], "estimatedPedestrians": 940,  "trafficTrend": "rising"},
    {"locationId": "loc_downtown_high_street",   "date": "2026-05-12", "hour": "18", "peakHours": ["12","13","18","19"], "estimatedPedestrians": 1050, "trafficTrend": "peak"},
    {"locationId": "loc_university_square",      "date": "2026-05-12", "hour": "14", "peakHours": ["11","12","14","15","18","19"], "estimatedPedestrians": 1150, "trafficTrend": "peak"},
    {"locationId": "loc_university_square",      "date": "2026-05-12", "hour": "19", "peakHours": ["11","12","14","15","18","19"], "estimatedPedestrians": 990,  "trafficTrend": "falling"},
    {"locationId": "loc_market_square",          "date": "2026-05-12", "hour": "10", "peakHours": ["10","11","16","17"], "estimatedPedestrians": 680,  "trafficTrend": "stable"},
    {"locationId": "loc_central_park",           "date": "2026-05-12", "hour": "15", "peakHours": ["15","16","17","18"], "estimatedPedestrians": 640,  "trafficTrend": "rising"},
    {"locationId": "loc_beach_area",             "date": "2026-05-12", "hour": "17", "peakHours": ["17","18","19","20"], "estimatedPedestrians": 750,  "trafficTrend": "rising"},
    {"locationId": "loc_residential_transit_hub","date": "2026-05-12", "hour": "08", "peakHours": ["07","08","17","18"], "estimatedPedestrians": 490,  "trafficTrend": "stable"},

    {"locationId": "loc_downtown_high_street",   "date": "2026-05-13", "hour": "12", "peakHours": ["12","13","18","19"], "estimatedPedestrians": 810,  "trafficTrend": "rising"},
    {"locationId": "loc_downtown_high_street",   "date": "2026-05-13", "hour": "18", "peakHours": ["12","13","18","19"], "estimatedPedestrians": 900,  "trafficTrend": "peak"},
    {"locationId": "loc_university_square",      "date": "2026-05-13", "hour": "14", "peakHours": ["11","12","14","15","18","19"], "estimatedPedestrians": 1000, "trafficTrend": "peak"},
    {"locationId": "loc_university_square",      "date": "2026-05-13", "hour": "19", "peakHours": ["11","12","14","15","18","19"], "estimatedPedestrians": 855,  "trafficTrend": "falling"},
    {"locationId": "loc_market_square",          "date": "2026-05-13", "hour": "10", "peakHours": ["10","11","16","17"], "estimatedPedestrians": 590,  "trafficTrend": "stable"},
    {"locationId": "loc_central_park",           "date": "2026-05-13", "hour": "15", "peakHours": ["15","16","17","18"], "estimatedPedestrians": 550,  "trafficTrend": "rising"},
    {"locationId": "loc_beach_area",             "date": "2026-05-13", "hour": "17", "peakHours": ["17","18","19","20"], "estimatedPedestrians": 650,  "trafficTrend": "rising"},
    {"locationId": "loc_residential_transit_hub","date": "2026-05-13", "hour": "08", "peakHours": ["07","08","17","18"], "estimatedPedestrians": 420,  "trafficTrend": "stable"},

    {"locationId": "loc_downtown_high_street",   "date": "2026-05-14", "hour": "12", "peakHours": ["12","13","18","19"], "estimatedPedestrians": 640,  "trafficTrend": "rising"},
    {"locationId": "loc_downtown_high_street",   "date": "2026-05-14", "hour": "18", "peakHours": ["12","13","18","19"], "estimatedPedestrians": 710,  "trafficTrend": "peak"},
    {"locationId": "loc_university_square",      "date": "2026-05-14", "hour": "14", "peakHours": ["11","12","14","15","18","19"], "estimatedPedestrians": 790,  "trafficTrend": "peak"},
    {"locationId": "loc_university_square",      "date": "2026-05-14", "hour": "19", "peakHours": ["11","12","14","15","18","19"], "estimatedPedestrians": 675,  "trafficTrend": "falling"},
    {"locationId": "loc_market_square",          "date": "2026-05-14", "hour": "10", "peakHours": ["10","11","16","17"], "estimatedPedestrians": 465,  "trafficTrend": "stable"},
    {"locationId": "loc_central_park",           "date": "2026-05-14", "hour": "15", "peakHours": ["15","16","17","18"], "estimatedPedestrians": 435,  "trafficTrend": "rising"},
    {"locationId": "loc_beach_area",             "date": "2026-05-14", "hour": "17", "peakHours": ["17","18","19","20"], "estimatedPedestrians": 510,  "trafficTrend": "rising"},
    {"locationId": "loc_residential_transit_hub","date": "2026-05-14", "hour": "08", "peakHours": ["07","08","17","18"], "estimatedPedestrians": 330,  "trafficTrend": "stable"},

    {"locationId": "loc_downtown_high_street",   "date": "2026-05-15", "hour": "12", "peakHours": ["12","13","18","19"], "estimatedPedestrians": 850,  "trafficTrend": "rising"},
    {"locationId": "loc_downtown_high_street",   "date": "2026-05-15", "hour": "18", "peakHours": ["12","13","18","19"], "estimatedPedestrians": 945,  "trafficTrend": "peak"},
    {"locationId": "loc_university_square",      "date": "2026-05-15", "hour": "14", "peakHours": ["11","12","14","15","18","19"], "estimatedPedestrians": 1050, "trafficTrend": "peak"},
    {"locationId": "loc_university_square",      "date": "2026-05-15", "hour": "19", "peakHours": ["11","12","14","15","18","19"], "estimatedPedestrians": 895,  "trafficTrend": "falling"},
    {"locationId": "loc_market_square",          "date": "2026-05-15", "hour": "10", "peakHours": ["10","11","16","17"], "estimatedPedestrians": 615,  "trafficTrend": "stable"},
    {"locationId": "loc_market_square",          "date": "2026-05-15", "hour": "16", "peakHours": ["10","11","16","17"], "estimatedPedestrians": 780,  "trafficTrend": "rising"},
    {"locationId": "loc_central_park",           "date": "2026-05-15", "hour": "15", "peakHours": ["15","16","17","18"], "estimatedPedestrians": 570,  "trafficTrend": "rising"},
    {"locationId": "loc_beach_area",             "date": "2026-05-15", "hour": "17", "peakHours": ["17","18","19","20"], "estimatedPedestrians": 670,  "trafficTrend": "rising"},
    {"locationId": "loc_residential_transit_hub","date": "2026-05-15", "hour": "08", "peakHours": ["07","08","17","18"], "estimatedPedestrians": 440,  "trafficTrend": "stable"},
    {"locationId": "loc_residential_transit_hub","date": "2026-05-15", "hour": "17", "peakHours": ["07","08","17","18"], "estimatedPedestrians": 600,  "trafficTrend": "peak"},

    {"locationId": "loc_downtown_high_street",   "date": "2026-05-16", "hour": "12", "peakHours": ["12","13","18","19"], "estimatedPedestrians": 660,  "trafficTrend": "rising"},
    {"locationId": "loc_downtown_high_street",   "date": "2026-05-16", "hour": "18", "peakHours": ["12","13","18","19"], "estimatedPedestrians": 720,  "trafficTrend": "peak"},
    {"locationId": "loc_university_square",      "date": "2026-05-16", "hour": "14", "peakHours": ["11","12","14","15","18","19"], "estimatedPedestrians": 792,  "trafficTrend": "peak"},
    {"locationId": "loc_university_square",      "date": "2026-05-16", "hour": "19", "peakHours": ["11","12","14","15","18","19"], "estimatedPedestrians": 726,  "trafficTrend": "falling"},
    {"locationId": "loc_market_square",          "date": "2026-05-16", "hour": "10", "peakHours": ["10","11","16","17"], "estimatedPedestrians": 990,  "trafficTrend": "stable"},
    {"locationId": "loc_central_park",           "date": "2026-05-16", "hour": "15", "peakHours": ["15","16","17","18"], "estimatedPedestrians": 1045, "trafficTrend": "rising"},
    {"locationId": "loc_beach_area",             "date": "2026-05-16", "hour": "17", "peakHours": ["17","18","19","20"], "estimatedPedestrians": 1320, "trafficTrend": "rising"},
    {"locationId": "loc_residential_transit_hub","date": "2026-05-16", "hour": "08", "peakHours": ["07","08","17","18"], "estimatedPedestrians": 290,  "trafficTrend": "stable"},

    {"locationId": "loc_downtown_high_street",   "date": "2026-05-17", "hour": "12", "peakHours": ["12","13","18","19"], "estimatedPedestrians": 590,  "trafficTrend": "rising"},
    {"locationId": "loc_downtown_high_street",   "date": "2026-05-17", "hour": "18", "peakHours": ["12","13","18","19"], "estimatedPedestrians": 650,  "trafficTrend": "peak"},
    {"locationId": "loc_university_square",      "date": "2026-05-17", "hour": "14", "peakHours": ["11","12","14","15","18","19"], "estimatedPedestrians": 715,  "trafficTrend": "peak"},
    {"locationId": "loc_university_square",      "date": "2026-05-17", "hour": "19", "peakHours": ["11","12","14","15","18","19"], "estimatedPedestrians": 660,  "trafficTrend": "falling"},
    {"locationId": "loc_market_square",          "date": "2026-05-17", "hour": "10", "peakHours": ["10","11","16","17"], "estimatedPedestrians": 825,  "trafficTrend": "stable"},
    {"locationId": "loc_central_park",           "date": "2026-05-17", "hour": "15", "peakHours": ["15","16","17","18"], "estimatedPedestrians": 968,  "trafficTrend": "rising"},
    {"locationId": "loc_central_park",           "date": "2026-05-17", "hour": "19", "peakHours": ["15","16","17","18","19","20"], "estimatedPedestrians": 750,  "trafficTrend": "peak"},
    {"locationId": "loc_beach_area",             "date": "2026-05-17", "hour": "17", "peakHours": ["17","18","19","20"], "estimatedPedestrians": 1210, "trafficTrend": "rising"},
    {"locationId": "loc_residential_transit_hub","date": "2026-05-17", "hour": "08", "peakHours": ["07","08","17","18"], "estimatedPedestrians": 250,  "trafficTrend": "stable"},

    {"locationId": "loc_downtown_high_street",   "date": "2026-05-18", "hour": "12", "peakHours": ["12","13","18","19"], "estimatedPedestrians": 770,  "trafficTrend": "rising"},
    {"locationId": "loc_downtown_high_street",   "date": "2026-05-18", "hour": "18", "peakHours": ["12","13","18","19"], "estimatedPedestrians": 855,  "trafficTrend": "peak"},
    {"locationId": "loc_university_square",      "date": "2026-05-18", "hour": "14", "peakHours": ["11","12","14","15","18","19"], "estimatedPedestrians": 950,  "trafficTrend": "peak"},
    {"locationId": "loc_university_square",      "date": "2026-05-18", "hour": "19", "peakHours": ["11","12","14","15","18","19"], "estimatedPedestrians": 813,  "trafficTrend": "falling"},
    {"locationId": "loc_market_square",          "date": "2026-05-18", "hour": "10", "peakHours": ["10","11","16","17"], "estimatedPedestrians": 560,  "trafficTrend": "stable"},
    {"locationId": "loc_central_park",           "date": "2026-05-18", "hour": "15", "peakHours": ["15","16","17","18"], "estimatedPedestrians": 520,  "trafficTrend": "rising"},
    {"locationId": "loc_beach_area",             "date": "2026-05-18", "hour": "17", "peakHours": ["17","18","19","20"], "estimatedPedestrians": 620,  "trafficTrend": "rising"},
    {"locationId": "loc_residential_transit_hub","date": "2026-05-18", "hour": "08", "peakHours": ["07","08","17","18"], "estimatedPedestrians": 400,  "trafficTrend": "stable"},

    {"locationId": "loc_downtown_high_street",   "date": "2026-05-19", "hour": "12", "peakHours": ["12","13","18","19"], "estimatedPedestrians": 950,  "trafficTrend": "rising"},
    {"locationId": "loc_downtown_high_street",   "date": "2026-05-19", "hour": "18", "peakHours": ["12","13","18","19"], "estimatedPedestrians": 1060, "trafficTrend": "peak"},
    {"locationId": "loc_university_square",      "date": "2026-05-19", "hour": "14", "peakHours": ["11","12","14","15","18","19"], "estimatedPedestrians": 1165, "trafficTrend": "peak"},
    {"locationId": "loc_university_square",      "date": "2026-05-19", "hour": "19", "peakHours": ["11","12","14","15","18","19"], "estimatedPedestrians": 998,  "trafficTrend": "falling"},
    {"locationId": "loc_market_square",          "date": "2026-05-19", "hour": "10", "peakHours": ["10","11","16","17"], "estimatedPedestrians": 690,  "trafficTrend": "stable"},
    {"locationId": "loc_central_park",           "date": "2026-05-19", "hour": "15", "peakHours": ["15","16","17","18"], "estimatedPedestrians": 645,  "trafficTrend": "rising"},
    {"locationId": "loc_beach_area",             "date": "2026-05-19", "hour": "17", "peakHours": ["17","18","19","20"], "estimatedPedestrians": 758,  "trafficTrend": "rising"},
    {"locationId": "loc_residential_transit_hub","date": "2026-05-19", "hour": "08", "peakHours": ["07","08","17","18"], "estimatedPedestrians": 495,  "trafficTrend": "stable"},
    {"locationId": "loc_residential_transit_hub","date": "2026-05-19", "hour": "17", "peakHours": ["07","08","17","18"], "estimatedPedestrians": 540,  "trafficTrend": "peak"},

    {"locationId": "loc_downtown_high_street",   "date": "2026-05-20", "hour": "12", "peakHours": ["12","13","18","19"], "estimatedPedestrians": 750,  "trafficTrend": "rising"},
    {"locationId": "loc_downtown_high_street",   "date": "2026-05-20", "hour": "18", "peakHours": ["12","13","18","19"], "estimatedPedestrians": 835,  "trafficTrend": "peak"},
    {"locationId": "loc_university_square",      "date": "2026-05-20", "hour": "14", "peakHours": ["11","12","14","15","18","19"], "estimatedPedestrians": 925,  "trafficTrend": "peak"},
    {"locationId": "loc_university_square",      "date": "2026-05-20", "hour": "19", "peakHours": ["11","12","14","15","18","19"], "estimatedPedestrians": 792,  "trafficTrend": "falling"},
    {"locationId": "loc_market_square",          "date": "2026-05-20", "hour": "10", "peakHours": ["10","11","16","17"], "estimatedPedestrians": 545,  "trafficTrend": "stable"},
    {"locationId": "loc_central_park",           "date": "2026-05-20", "hour": "15", "peakHours": ["15","16","17","18"], "estimatedPedestrians": 510,  "trafficTrend": "rising"},
    {"locationId": "loc_beach_area",             "date": "2026-05-20", "hour": "17", "peakHours": ["17","18","19","20"], "estimatedPedestrians": 598,  "trafficTrend": "rising"},
    {"locationId": "loc_residential_transit_hub","date": "2026-05-20", "hour": "08", "peakHours": ["07","08","17","18"], "estimatedPedestrians": 390,  "trafficTrend": "stable"},

    {"locationId": "loc_downtown_high_street",   "date": "2026-05-21", "hour": "12", "peakHours": ["12","13","18","19"], "estimatedPedestrians": 985,  "trafficTrend": "rising"},
    {"locationId": "loc_downtown_high_street",   "date": "2026-05-21", "hour": "18", "peakHours": ["12","13","18","19"], "estimatedPedestrians": 1100, "trafficTrend": "peak"},
    {"locationId": "loc_university_square",      "date": "2026-05-21", "hour": "14", "peakHours": ["11","12","14","15","18","19"], "estimatedPedestrians": 1210, "trafficTrend": "peak"},
    {"locationId": "loc_university_square",      "date": "2026-05-21", "hour": "19", "peakHours": ["11","12","14","15","18","19"], "estimatedPedestrians": 1034, "trafficTrend": "falling"},
    {"locationId": "loc_market_square",          "date": "2026-05-21", "hour": "10", "peakHours": ["10","11","16","17"], "estimatedPedestrians": 715,  "trafficTrend": "stable"},
    {"locationId": "loc_central_park",           "date": "2026-05-21", "hour": "15", "peakHours": ["15","16","17","18"], "estimatedPedestrians": 668,  "trafficTrend": "rising"},
    {"locationId": "loc_beach_area",             "date": "2026-05-21", "hour": "17", "peakHours": ["17","18","19","20"], "estimatedPedestrians": 784,  "trafficTrend": "rising"},
    {"locationId": "loc_residential_transit_hub","date": "2026-05-21", "hour": "08", "peakHours": ["07","08","17","18"], "estimatedPedestrians": 511,  "trafficTrend": "stable"},

    {"locationId": "loc_downtown_high_street",   "date": "2026-05-22", "hour": "12", "peakHours": ["12","13","18","19"], "estimatedPedestrians": 1020, "trafficTrend": "rising"},
    {"locationId": "loc_downtown_high_street",   "date": "2026-05-22", "hour": "18", "peakHours": ["12","13","18","19"], "estimatedPedestrians": 1140, "trafficTrend": "peak"},
    {"locationId": "loc_university_square",      "date": "2026-05-22", "hour": "14", "peakHours": ["11","12","14","15","18","19"], "estimatedPedestrians": 1260, "trafficTrend": "peak"},
    {"locationId": "loc_university_square",      "date": "2026-05-22", "hour": "19", "peakHours": ["11","12","14","15","18","19"], "estimatedPedestrians": 1077, "trafficTrend": "falling"},
    {"locationId": "loc_market_square",          "date": "2026-05-22", "hour": "10", "peakHours": ["10","11","16","17"], "estimatedPedestrians": 745,  "trafficTrend": "stable"},
    {"locationId": "loc_market_square",          "date": "2026-05-22", "hour": "16", "peakHours": ["10","11","16","17"], "estimatedPedestrians": 940,  "trafficTrend": "rising"},
    {"locationId": "loc_central_park",           "date": "2026-05-22", "hour": "15", "peakHours": ["15","16","17","18"], "estimatedPedestrians": 695,  "trafficTrend": "rising"},
    {"locationId": "loc_beach_area",             "date": "2026-05-22", "hour": "17", "peakHours": ["17","18","19","20"], "estimatedPedestrians": 815,  "trafficTrend": "rising"},
    {"locationId": "loc_residential_transit_hub","date": "2026-05-22", "hour": "08", "peakHours": ["07","08","17","18"], "estimatedPedestrians": 530,  "trafficTrend": "stable"},
    {"locationId": "loc_residential_transit_hub","date": "2026-05-22", "hour": "17", "peakHours": ["07","08","17","18"], "estimatedPedestrians": 625,  "trafficTrend": "peak"},

    {"locationId": "loc_downtown_high_street",   "date": "2026-05-23", "hour": "12", "peakHours": ["12","13","18","19"], "estimatedPedestrians": 450,  "trafficTrend": "stable"},
    {"locationId": "loc_downtown_high_street",   "date": "2026-05-23", "hour": "18", "peakHours": ["12","13","18","19"], "estimatedPedestrians": 490,  "trafficTrend": "peak"},
    {"locationId": "loc_university_square",      "date": "2026-05-23", "hour": "14", "peakHours": ["11","12","14","15","18","19"], "estimatedPedestrians": 540,  "trafficTrend": "peak"},
    {"locationId": "loc_university_square",      "date": "2026-05-23", "hour": "19", "peakHours": ["11","12","14","15","18","19"], "estimatedPedestrians": 495,  "trafficTrend": "falling"},
    {"locationId": "loc_market_square",          "date": "2026-05-23", "hour": "10", "peakHours": ["10","11","16","17"], "estimatedPedestrians": 675,  "trafficTrend": "stable"},
    {"locationId": "loc_central_park",           "date": "2026-05-23", "hour": "15", "peakHours": ["15","16","17","18"], "estimatedPedestrians": 712,  "trafficTrend": "rising"},
    {"locationId": "loc_beach_area",             "date": "2026-05-23", "hour": "17", "peakHours": ["17","18","19","20"], "estimatedPedestrians": 900,  "trafficTrend": "rising"},
    {"locationId": "loc_residential_transit_hub","date": "2026-05-23", "hour": "08", "peakHours": ["07","08","17","18"], "estimatedPedestrians": 200,  "trafficTrend": "stable"},

    {"locationId": "loc_downtown_high_street",   "date": "2026-05-24", "hour": "12", "peakHours": ["12","13","18","19"], "estimatedPedestrians": 565,  "trafficTrend": "rising"},
    {"locationId": "loc_downtown_high_street",   "date": "2026-05-24", "hour": "18", "peakHours": ["12","13","18","19"], "estimatedPedestrians": 618,  "trafficTrend": "peak"},
    {"locationId": "loc_university_square",      "date": "2026-05-24", "hour": "14", "peakHours": ["11","12","14","15","18","19"], "estimatedPedestrians": 684,  "trafficTrend": "peak"},
    {"locationId": "loc_university_square",      "date": "2026-05-24", "hour": "19", "peakHours": ["11","12","14","15","18","19"], "estimatedPedestrians": 627,  "trafficTrend": "falling"},
    {"locationId": "loc_market_square",          "date": "2026-05-24", "hour": "10", "peakHours": ["10","11","16","17"], "estimatedPedestrians": 855,  "trafficTrend": "stable"},
    {"locationId": "loc_central_park",           "date": "2026-05-24", "hour": "15", "peakHours": ["15","16","17","18"], "estimatedPedestrians": 836,  "trafficTrend": "rising"},
    {"locationId": "loc_central_park",           "date": "2026-05-24", "hour": "19", "peakHours": ["15","16","17","18","19","20"], "estimatedPedestrians": 620,  "trafficTrend": "peak"},
    {"locationId": "loc_beach_area",             "date": "2026-05-24", "hour": "17", "peakHours": ["17","18","19","20"], "estimatedPedestrians": 1045, "trafficTrend": "rising"},
    {"locationId": "loc_residential_transit_hub","date": "2026-05-24", "hour": "08", "peakHours": ["07","08","17","18"], "estimatedPedestrians": 245,  "trafficTrend": "stable"},

    {"locationId": "loc_downtown_high_street",   "date": "2026-05-25", "hour": "12", "peakHours": ["12","13","18","19"], "estimatedPedestrians": 930,  "trafficTrend": "rising"},
    {"locationId": "loc_downtown_high_street",   "date": "2026-05-25", "hour": "18", "peakHours": ["12","13","18","19"], "estimatedPedestrians": 1040, "trafficTrend": "peak"},
    {"locationId": "loc_university_square",      "date": "2026-05-25", "hour": "14", "peakHours": ["11","12","14","15","18","19"], "estimatedPedestrians": 1140, "trafficTrend": "peak"},
    {"locationId": "loc_university_square",      "date": "2026-05-25", "hour": "19", "peakHours": ["11","12","14","15","18","19"], "estimatedPedestrians": 975,  "trafficTrend": "falling"},
    {"locationId": "loc_market_square",          "date": "2026-05-25", "hour": "10", "peakHours": ["10","11","16","17"], "estimatedPedestrians": 675,  "trafficTrend": "stable"},
    {"locationId": "loc_central_park",           "date": "2026-05-25", "hour": "15", "peakHours": ["15","16","17","18"], "estimatedPedestrians": 630,  "trafficTrend": "rising"},
    {"locationId": "loc_beach_area",             "date": "2026-05-25", "hour": "17", "peakHours": ["17","18","19","20"], "estimatedPedestrians": 740,  "trafficTrend": "rising"},
    {"locationId": "loc_residential_transit_hub","date": "2026-05-25", "hour": "08", "peakHours": ["07","08","17","18"], "estimatedPedestrians": 485,  "trafficTrend": "stable"},

    {"locationId": "loc_downtown_high_street",   "date": "2026-05-26", "hour": "12", "peakHours": ["12","13","18","19"], "estimatedPedestrians": 1000, "trafficTrend": "rising"},
    {"locationId": "loc_downtown_high_street",   "date": "2026-05-26", "hour": "18", "peakHours": ["12","13","18","19"], "estimatedPedestrians": 1120, "trafficTrend": "peak"},
    {"locationId": "loc_university_square",      "date": "2026-05-26", "hour": "14", "peakHours": ["11","12","14","15","18","19"], "estimatedPedestrians": 1230, "trafficTrend": "peak"},
    {"locationId": "loc_university_square",      "date": "2026-05-26", "hour": "19", "peakHours": ["11","12","14","15","18","19"], "estimatedPedestrians": 1052, "trafficTrend": "falling"},
    {"locationId": "loc_market_square",          "date": "2026-05-26", "hour": "10", "peakHours": ["10","11","16","17"], "estimatedPedestrians": 730,  "trafficTrend": "stable"},
    {"locationId": "loc_central_park",           "date": "2026-05-26", "hour": "15", "peakHours": ["15","16","17","18"], "estimatedPedestrians": 682,  "trafficTrend": "rising"},
    {"locationId": "loc_beach_area",             "date": "2026-05-26", "hour": "17", "peakHours": ["17","18","19","20"], "estimatedPedestrians": 800,  "trafficTrend": "rising"},
    {"locationId": "loc_residential_transit_hub","date": "2026-05-26", "hour": "08", "peakHours": ["07","08","17","18"], "estimatedPedestrians": 520,  "trafficTrend": "stable"},
    {"locationId": "loc_residential_transit_hub","date": "2026-05-26", "hour": "17", "peakHours": ["07","08","17","18"], "estimatedPedestrians": 545,  "trafficTrend": "peak"},

    {"locationId": "loc_downtown_high_street",   "date": "2026-05-27", "hour": "12", "peakHours": ["12","13","18","19"], "estimatedPedestrians": 835,  "trafficTrend": "rising"},
    {"locationId": "loc_downtown_high_street",   "date": "2026-05-27", "hour": "18", "peakHours": ["12","13","18","19"], "estimatedPedestrians": 930,  "trafficTrend": "peak"},
    {"locationId": "loc_university_square",      "date": "2026-05-27", "hour": "14", "peakHours": ["11","12","14","15","18","19"], "estimatedPedestrians": 1025, "trafficTrend": "peak"},
    {"locationId": "loc_university_square",      "date": "2026-05-27", "hour": "19", "peakHours": ["11","12","14","15","18","19"], "estimatedPedestrians": 877,  "trafficTrend": "falling"},
    {"locationId": "loc_market_square",          "date": "2026-05-27", "hour": "10", "peakHours": ["10","11","16","17"], "estimatedPedestrians": 605,  "trafficTrend": "stable"},
    {"locationId": "loc_central_park",           "date": "2026-05-27", "hour": "15", "peakHours": ["15","16","17","18"], "estimatedPedestrians": 566,  "trafficTrend": "rising"},
    {"locationId": "loc_beach_area",             "date": "2026-05-27", "hour": "17", "peakHours": ["17","18","19","20"], "estimatedPedestrians": 664,  "trafficTrend": "rising"},
    {"locationId": "loc_residential_transit_hub","date": "2026-05-27", "hour": "08", "peakHours": ["07","08","17","18"], "estimatedPedestrians": 430,  "trafficTrend": "stable"},

    {"locationId": "loc_downtown_high_street",   "date": "2026-05-28", "hour": "12", "peakHours": ["12","13","18","19"], "estimatedPedestrians": 510,  "trafficTrend": "stable"},
    {"locationId": "loc_downtown_high_street",   "date": "2026-05-28", "hour": "18", "peakHours": ["12","13","18","19"], "estimatedPedestrians": 570,  "trafficTrend": "peak"},
    {"locationId": "loc_university_square",      "date": "2026-05-28", "hour": "14", "peakHours": ["11","12","14","15","18","19"], "estimatedPedestrians": 630,  "trafficTrend": "stable"},
    {"locationId": "loc_university_square",      "date": "2026-05-28", "hour": "19", "peakHours": ["11","12","14","15","18","19"], "estimatedPedestrians": 540,  "trafficTrend": "falling"},
    {"locationId": "loc_market_square",          "date": "2026-05-28", "hour": "10", "peakHours": ["10","11","16","17"], "estimatedPedestrians": 372,  "trafficTrend": "stable"},
    {"locationId": "loc_central_park",           "date": "2026-05-28", "hour": "15", "peakHours": ["15","16","17","18"], "estimatedPedestrians": 348,  "trafficTrend": "stable"},
    {"locationId": "loc_beach_area",             "date": "2026-05-28", "hour": "17", "peakHours": ["17","18","19","20"], "estimatedPedestrians": 408,  "trafficTrend": "stable"},
    {"locationId": "loc_residential_transit_hub","date": "2026-05-28", "hour": "08", "peakHours": ["07","08","17","18"], "estimatedPedestrians": 265,  "trafficTrend": "stable"},

    {"locationId": "loc_downtown_high_street",   "date": "2026-05-29", "hour": "12", "peakHours": ["12","13","18","19"], "estimatedPedestrians": 800,  "trafficTrend": "rising"},
    {"locationId": "loc_downtown_high_street",   "date": "2026-05-29", "hour": "18", "peakHours": ["12","13","18","19"], "estimatedPedestrians": 890,  "trafficTrend": "peak"},
    {"locationId": "loc_university_square",      "date": "2026-05-29", "hour": "14", "peakHours": ["11","12","14","15","18","19"], "estimatedPedestrians": 990,  "trafficTrend": "peak"},
    {"locationId": "loc_university_square",      "date": "2026-05-29", "hour": "19", "peakHours": ["11","12","14","15","18","19"], "estimatedPedestrians": 845,  "trafficTrend": "falling"},
    {"locationId": "loc_market_square",          "date": "2026-05-29", "hour": "10", "peakHours": ["10","11","16","17"], "estimatedPedestrians": 585,  "trafficTrend": "stable"},
    {"locationId": "loc_market_square",          "date": "2026-05-29", "hour": "16", "peakHours": ["10","11","16","17"], "estimatedPedestrians": 735,  "trafficTrend": "rising"},
    {"locationId": "loc_central_park",           "date": "2026-05-29", "hour": "15", "peakHours": ["15","16","17","18"], "estimatedPedestrians": 545,  "trafficTrend": "rising"},
    {"locationId": "loc_beach_area",             "date": "2026-05-29", "hour": "17", "peakHours": ["17","18","19","20"], "estimatedPedestrians": 640,  "trafficTrend": "rising"},
    {"locationId": "loc_residential_transit_hub","date": "2026-05-29", "hour": "08", "peakHours": ["07","08","17","18"], "estimatedPedestrians": 420,  "trafficTrend": "stable"},

    {"locationId": "loc_downtown_high_street",   "date": "2026-05-30", "hour": "12", "peakHours": ["12","13","18","19"], "estimatedPedestrians": 720,  "trafficTrend": "rising"},
    {"locationId": "loc_downtown_high_street",   "date": "2026-05-30", "hour": "18", "peakHours": ["12","13","18","19"], "estimatedPedestrians": 795,  "trafficTrend": "peak"},
    {"locationId": "loc_university_square",      "date": "2026-05-30", "hour": "14", "peakHours": ["11","12","14","15","18","19"], "estimatedPedestrians": 870,  "trafficTrend": "peak"},
    {"locationId": "loc_university_square",      "date": "2026-05-30", "hour": "19", "peakHours": ["11","12","14","15","18","19"], "estimatedPedestrians": 800,  "trafficTrend": "falling"},
    {"locationId": "loc_market_square",          "date": "2026-05-30", "hour": "10", "peakHours": ["10","11","16","17"], "estimatedPedestrians": 1090, "trafficTrend": "stable"},
    {"locationId": "loc_central_park",           "date": "2026-05-30", "hour": "15", "peakHours": ["15","16","17","18"], "estimatedPedestrians": 1145, "trafficTrend": "rising"},
    {"locationId": "loc_central_park",           "date": "2026-05-30", "hour": "19", "peakHours": ["15","16","17","18","19","20"], "estimatedPedestrians": 1150, "trafficTrend": "peak"},
    {"locationId": "loc_beach_area",             "date": "2026-05-30", "hour": "17", "peakHours": ["17","18","19","20"], "estimatedPedestrians": 1450, "trafficTrend": "rising"},
    {"locationId": "loc_residential_transit_hub","date": "2026-05-30", "hour": "08", "peakHours": ["07","08","17","18"], "estimatedPedestrians": 310,  "trafficTrend": "stable"},

    {"locationId": "loc_downtown_high_street",   "date": "2026-05-31", "hour": "12", "peakHours": ["12","13","18","19"], "estimatedPedestrians": 680,  "trafficTrend": "rising"},
    {"locationId": "loc_downtown_high_street",   "date": "2026-05-31", "hour": "18", "peakHours": ["12","13","18","19"], "estimatedPedestrians": 750,  "trafficTrend": "peak"},
    {"locationId": "loc_university_square",      "date": "2026-05-31", "hour": "14", "peakHours": ["11","12","14","15","18","19"], "estimatedPedestrians": 825,  "trafficTrend": "peak"},
    {"locationId": "loc_university_square",      "date": "2026-05-31", "hour": "19", "peakHours": ["11","12","14","15","18","19"], "estimatedPedestrians": 760,  "trafficTrend": "falling"},
    {"locationId": "loc_market_square",          "date": "2026-05-31", "hour": "10", "peakHours": ["10","11","16","17"], "estimatedPedestrians": 950,  "trafficTrend": "stable"},
    {"locationId": "loc_central_park",           "date": "2026-05-31", "hour": "15", "peakHours": ["15","16","17","18"], "estimatedPedestrians": 1070, "trafficTrend": "rising"},
    {"locationId": "loc_beach_area",             "date": "2026-05-31", "hour": "17", "peakHours": ["17","18","19","20"], "estimatedPedestrians": 1380, "trafficTrend": "rising"},
    {"locationId": "loc_residential_transit_hub","date": "2026-05-31", "hour": "08", "peakHours": ["07","08","17","18"], "estimatedPedestrians": 280,  "trafficTrend": "stable"},

    {"locationId": "loc_downtown_high_street",   "date": "2026-06-01", "hour": "12", "peakHours": ["12","13","18","19"], "estimatedPedestrians": 870,  "trafficTrend": "rising"},
    {"locationId": "loc_downtown_high_street",   "date": "2026-06-01", "hour": "18", "peakHours": ["12","13","18","19"], "estimatedPedestrians": 970,  "trafficTrend": "peak"},
    {"locationId": "loc_university_square",      "date": "2026-06-01", "hour": "14", "peakHours": ["11","12","14","15","18","19"], "estimatedPedestrians": 1070, "trafficTrend": "peak"},
    {"locationId": "loc_university_square",      "date": "2026-06-01", "hour": "19", "peakHours": ["11","12","14","15","18","19"], "estimatedPedestrians": 915,  "trafficTrend": "falling"},
    {"locationId": "loc_market_square",          "date": "2026-06-01", "hour": "10", "peakHours": ["10","11","16","17"], "estimatedPedestrians": 640,  "trafficTrend": "stable"},
    {"locationId": "loc_central_park",           "date": "2026-06-01", "hour": "15", "peakHours": ["15","16","17","18"], "estimatedPedestrians": 596,  "trafficTrend": "rising"},
    {"locationId": "loc_beach_area",             "date": "2026-06-01", "hour": "17", "peakHours": ["17","18","19","20"], "estimatedPedestrians": 700,  "trafficTrend": "rising"},
    {"locationId": "loc_residential_transit_hub","date": "2026-06-01", "hour": "08", "peakHours": ["07","08","17","18"], "estimatedPedestrians": 450,  "trafficTrend": "stable"},

    {"locationId": "loc_downtown_high_street",   "date": "2026-06-02", "hour": "12", "peakHours": ["12","13","18","19"], "estimatedPedestrians": 1030, "trafficTrend": "rising"},
    {"locationId": "loc_downtown_high_street",   "date": "2026-06-02", "hour": "18", "peakHours": ["12","13","18","19"], "estimatedPedestrians": 1150, "trafficTrend": "peak"},
    {"locationId": "loc_university_square",      "date": "2026-06-02", "hour": "14", "peakHours": ["11","12","14","15","18","19"], "estimatedPedestrians": 1265, "trafficTrend": "peak"},
    {"locationId": "loc_university_square",      "date": "2026-06-02", "hour": "19", "peakHours": ["11","12","14","15","18","19"], "estimatedPedestrians": 1082, "trafficTrend": "falling"},
    {"locationId": "loc_market_square",          "date": "2026-06-02", "hour": "10", "peakHours": ["10","11","16","17"], "estimatedPedestrians": 750,  "trafficTrend": "stable"},
    {"locationId": "loc_central_park",           "date": "2026-06-02", "hour": "15", "peakHours": ["15","16","17","18"], "estimatedPedestrians": 700,  "trafficTrend": "rising"},
    {"locationId": "loc_beach_area",             "date": "2026-06-02", "hour": "17", "peakHours": ["17","18","19","20"], "estimatedPedestrians": 822,  "trafficTrend": "rising"},
    {"locationId": "loc_residential_transit_hub","date": "2026-06-02", "hour": "08", "peakHours": ["07","08","17","18"], "estimatedPedestrians": 534,  "trafficTrend": "stable"},
    {"locationId": "loc_residential_transit_hub","date": "2026-06-02", "hour": "17", "peakHours": ["07","08","17","18"], "estimatedPedestrians": 558,  "trafficTrend": "peak"},

    {"locationId": "loc_downtown_high_street",   "date": "2026-06-03", "hour": "12", "peakHours": ["12","13","18","19"], "estimatedPedestrians": 1050, "trafficTrend": "rising"},
    {"locationId": "loc_downtown_high_street",   "date": "2026-06-03", "hour": "18", "peakHours": ["12","13","18","19"], "estimatedPedestrians": 1170, "trafficTrend": "peak"},
    {"locationId": "loc_university_square",      "date": "2026-06-03", "hour": "14", "peakHours": ["11","12","14","15","18","19"], "estimatedPedestrians": 1290, "trafficTrend": "peak"},
    {"locationId": "loc_university_square",      "date": "2026-06-03", "hour": "19", "peakHours": ["11","12","14","15","18","19"], "estimatedPedestrians": 1103, "trafficTrend": "falling"},
    {"locationId": "loc_market_square",          "date": "2026-06-03", "hour": "10", "peakHours": ["10","11","16","17"], "estimatedPedestrians": 765,  "trafficTrend": "stable"},
    {"locationId": "loc_central_park",           "date": "2026-06-03", "hour": "15", "peakHours": ["15","16","17","18"], "estimatedPedestrians": 714,  "trafficTrend": "rising"},
    {"locationId": "loc_beach_area",             "date": "2026-06-03", "hour": "17", "peakHours": ["17","18","19","20"], "estimatedPedestrians": 838,  "trafficTrend": "rising"},
    {"locationId": "loc_residential_transit_hub","date": "2026-06-03", "hour": "08", "peakHours": ["07","08","17","18"], "estimatedPedestrians": 545,  "trafficTrend": "stable"},

    {"locationId": "loc_downtown_high_street",   "date": "2026-06-04", "hour": "12", "peakHours": ["12","13","18","19"], "estimatedPedestrians": 680,  "trafficTrend": "rising"},
    {"locationId": "loc_downtown_high_street",   "date": "2026-06-04", "hour": "18", "peakHours": ["12","13","18","19"], "estimatedPedestrians": 760,  "trafficTrend": "peak"},
    {"locationId": "loc_university_square",      "date": "2026-06-04", "hour": "14", "peakHours": ["11","12","14","15","18","19"], "estimatedPedestrians": 838,  "trafficTrend": "peak"},
    {"locationId": "loc_university_square",      "date": "2026-06-04", "hour": "19", "peakHours": ["11","12","14","15","18","19"], "estimatedPedestrians": 716,  "trafficTrend": "falling"},
    {"locationId": "loc_market_square",          "date": "2026-06-04", "hour": "10", "peakHours": ["10","11","16","17"], "estimatedPedestrians": 495,  "trafficTrend": "stable"},
    {"locationId": "loc_central_park",           "date": "2026-06-04", "hour": "15", "peakHours": ["15","16","17","18"], "estimatedPedestrians": 462,  "trafficTrend": "rising"},
    {"locationId": "loc_beach_area",             "date": "2026-06-04", "hour": "17", "peakHours": ["17","18","19","20"], "estimatedPedestrians": 542,  "trafficTrend": "rising"},
    {"locationId": "loc_residential_transit_hub","date": "2026-06-04", "hour": "08", "peakHours": ["07","08","17","18"], "estimatedPedestrians": 352,  "trafficTrend": "stable"},

    {"locationId": "loc_downtown_high_street",   "date": "2026-06-05", "hour": "12", "peakHours": ["12","13","18","19"], "estimatedPedestrians": 870,  "trafficTrend": "rising"},
    {"locationId": "loc_downtown_high_street",   "date": "2026-06-05", "hour": "18", "peakHours": ["12","13","18","19"], "estimatedPedestrians": 970,  "trafficTrend": "peak"},
    {"locationId": "loc_university_square",      "date": "2026-06-05", "hour": "14", "peakHours": ["11","12","14","15","18","19"], "estimatedPedestrians": 1070, "trafficTrend": "peak"},
    {"locationId": "loc_university_square",      "date": "2026-06-05", "hour": "19", "peakHours": ["11","12","14","15","18","19"], "estimatedPedestrians": 913,  "trafficTrend": "falling"},
    {"locationId": "loc_market_square",          "date": "2026-06-05", "hour": "10", "peakHours": ["10","11","16","17"], "estimatedPedestrians": 635,  "trafficTrend": "stable"},
    {"locationId": "loc_market_square",          "date": "2026-06-05", "hour": "16", "peakHours": ["10","11","16","17"], "estimatedPedestrians": 800,  "trafficTrend": "rising"},
    {"locationId": "loc_central_park",           "date": "2026-06-05", "hour": "15", "peakHours": ["15","16","17","18"], "estimatedPedestrians": 592,  "trafficTrend": "rising"},
    {"locationId": "loc_beach_area",             "date": "2026-06-05", "hour": "17", "peakHours": ["17","18","19","20"], "estimatedPedestrians": 696,  "trafficTrend": "rising"},
    {"locationId": "loc_residential_transit_hub","date": "2026-06-05", "hour": "08", "peakHours": ["07","08","17","18"], "estimatedPedestrians": 452,  "trafficTrend": "stable"},

    {"locationId": "loc_downtown_high_street",   "date": "2026-06-06", "hour": "12", "peakHours": ["12","13","18","19"], "estimatedPedestrians": 770,  "trafficTrend": "rising"},
    {"locationId": "loc_downtown_high_street",   "date": "2026-06-06", "hour": "18", "peakHours": ["12","13","18","19"], "estimatedPedestrians": 850,  "trafficTrend": "peak"},
    {"locationId": "loc_university_square",      "date": "2026-06-06", "hour": "14", "peakHours": ["11","12","14","15","18","19"], "estimatedPedestrians": 935,  "trafficTrend": "peak"},
    {"locationId": "loc_university_square",      "date": "2026-06-06", "hour": "19", "peakHours": ["11","12","14","15","18","19"], "estimatedPedestrians": 858,  "trafficTrend": "falling"},
    {"locationId": "loc_market_square",          "date": "2026-06-06", "hour": "10", "peakHours": ["10","11","16","17"], "estimatedPedestrians": 1170, "trafficTrend": "stable"},
    {"locationId": "loc_central_park",           "date": "2026-06-06", "hour": "15", "peakHours": ["15","16","17","18"], "estimatedPedestrians": 1230, "trafficTrend": "rising"},
    {"locationId": "loc_central_park",           "date": "2026-06-06", "hour": "19", "peakHours": ["15","16","17","18","19","20"], "estimatedPedestrians": 1250, "trafficTrend": "peak"},
    {"locationId": "loc_beach_area",             "date": "2026-06-06", "hour": "17", "peakHours": ["17","18","19","20"], "estimatedPedestrians": 1560, "trafficTrend": "rising"},
    {"locationId": "loc_residential_transit_hub","date": "2026-06-06", "hour": "08", "peakHours": ["07","08","17","18"], "estimatedPedestrians": 330,  "trafficTrend": "stable"},

    {"locationId": "loc_downtown_high_street",   "date": "2026-06-07", "hour": "12", "peakHours": ["12","13","18","19"], "estimatedPedestrians": 730,  "trafficTrend": "rising"},
    {"locationId": "loc_downtown_high_street",   "date": "2026-06-07", "hour": "18", "peakHours": ["12","13","18","19"], "estimatedPedestrians": 806,  "trafficTrend": "peak"},
    {"locationId": "loc_university_square",      "date": "2026-06-07", "hour": "14", "peakHours": ["11","12","14","15","18","19"], "estimatedPedestrians": 886,  "trafficTrend": "peak"},
    {"locationId": "loc_university_square",      "date": "2026-06-07", "hour": "19", "peakHours": ["11","12","14","15","18","19"], "estimatedPedestrians": 815,  "trafficTrend": "falling"},
    {"locationId": "loc_market_square",          "date": "2026-06-07", "hour": "10", "peakHours": ["10","11","16","17"], "estimatedPedestrians": 1085, "trafficTrend": "stable"},
    {"locationId": "loc_central_park",           "date": "2026-06-07", "hour": "15", "peakHours": ["15","16","17","18"], "estimatedPedestrians": 1145, "trafficTrend": "rising"},
    {"locationId": "loc_central_park",           "date": "2026-06-07", "hour": "19", "peakHours": ["15","16","17","18","19","20"], "estimatedPedestrians": 1180, "trafficTrend": "peak"},
    {"locationId": "loc_beach_area",             "date": "2026-06-07", "hour": "17", "peakHours": ["17","18","19","20"], "estimatedPedestrians": 1450, "trafficTrend": "rising"},
    {"locationId": "loc_residential_transit_hub","date": "2026-06-07", "hour": "08", "peakHours": ["07","08","17","18"], "estimatedPedestrians": 310,  "trafficTrend": "stable"},

    {"locationId": "loc_downtown_high_street",   "date": "2026-06-08", "hour": "12", "peakHours": ["12","13","18","19"], "estimatedPedestrians": 748,  "trafficTrend": "rising"},
    {"locationId": "loc_downtown_high_street",   "date": "2026-06-08", "hour": "18", "peakHours": ["12","13","18","19"], "estimatedPedestrians": 833,  "trafficTrend": "peak"},
    {"locationId": "loc_university_square",      "date": "2026-06-08", "hour": "14", "peakHours": ["11","12","14","15","18","19"], "estimatedPedestrians": 920,  "trafficTrend": "peak"},
    {"locationId": "loc_university_square",      "date": "2026-06-08", "hour": "19", "peakHours": ["11","12","14","15","18","19"], "estimatedPedestrians": 786,  "trafficTrend": "falling"},
    {"locationId": "loc_market_square",          "date": "2026-06-08", "hour": "10", "peakHours": ["10","11","16","17"], "estimatedPedestrians": 545,  "trafficTrend": "stable"},
    {"locationId": "loc_central_park",           "date": "2026-06-08", "hour": "15", "peakHours": ["15","16","17","18"], "estimatedPedestrians": 509,  "trafficTrend": "rising"},
    {"locationId": "loc_beach_area",             "date": "2026-06-08", "hour": "17", "peakHours": ["17","18","19","20"], "estimatedPedestrians": 598,  "trafficTrend": "rising"},
    {"locationId": "loc_residential_transit_hub","date": "2026-06-08", "hour": "08", "peakHours": ["07","08","17","18"], "estimatedPedestrians": 387,  "trafficTrend": "stable"},

    {"locationId": "loc_downtown_high_street",   "date": "2026-06-09", "hour": "12", "peakHours": ["12","13","18","19"], "estimatedPedestrians": 1020, "trafficTrend": "rising"},
    {"locationId": "loc_downtown_high_street",   "date": "2026-06-09", "hour": "18", "peakHours": ["12","13","18","19"], "estimatedPedestrians": 1138, "trafficTrend": "peak"},
    {"locationId": "loc_university_square",      "date": "2026-06-09", "hour": "14", "peakHours": ["11","12","14","15","18","19"], "estimatedPedestrians": 1252, "trafficTrend": "peak"},
    {"locationId": "loc_university_square",      "date": "2026-06-09", "hour": "19", "peakHours": ["11","12","14","15","18","19"], "estimatedPedestrians": 1071, "trafficTrend": "falling"},
    {"locationId": "loc_market_square",          "date": "2026-06-09", "hour": "10", "peakHours": ["10","11","16","17"], "estimatedPedestrians": 743,  "trafficTrend": "stable"},
    {"locationId": "loc_central_park",           "date": "2026-06-09", "hour": "15", "peakHours": ["15","16","17","18"], "estimatedPedestrians": 694,  "trafficTrend": "rising"},
    {"locationId": "loc_beach_area",             "date": "2026-06-09", "hour": "17", "peakHours": ["17","18","19","20"], "estimatedPedestrians": 814,  "trafficTrend": "rising"},
    {"locationId": "loc_residential_transit_hub","date": "2026-06-09", "hour": "08", "peakHours": ["07","08","17","18"], "estimatedPedestrians": 529,  "trafficTrend": "stable"},
    {"locationId": "loc_residential_transit_hub","date": "2026-06-09", "hour": "17", "peakHours": ["07","08","17","18"], "estimatedPedestrians": 554,  "trafficTrend": "peak"},

    {"locationId": "loc_downtown_high_street",   "date": "2026-06-10", "hour": "12", "peakHours": ["12","13","18","19"], "estimatedPedestrians": 1040, "trafficTrend": "rising"},
    {"locationId": "loc_downtown_high_street",   "date": "2026-06-10", "hour": "18", "peakHours": ["12","13","18","19"], "estimatedPedestrians": 1162, "trafficTrend": "peak"},
    {"locationId": "loc_university_square",      "date": "2026-06-10", "hour": "14", "peakHours": ["11","12","14","15","18","19"], "estimatedPedestrians": 1278, "trafficTrend": "peak"},
    {"locationId": "loc_university_square",      "date": "2026-06-10", "hour": "19", "peakHours": ["11","12","14","15","18","19"], "estimatedPedestrians": 1093, "trafficTrend": "falling"},
    {"locationId": "loc_market_square",          "date": "2026-06-10", "hour": "10", "peakHours": ["10","11","16","17"], "estimatedPedestrians": 758,  "trafficTrend": "stable"},
    {"locationId": "loc_central_park",           "date": "2026-06-10", "hour": "15", "peakHours": ["15","16","17","18"], "estimatedPedestrians": 708,  "trafficTrend": "rising"},
    {"locationId": "loc_beach_area",             "date": "2026-06-10", "hour": "17", "peakHours": ["17","18","19","20"], "estimatedPedestrians": 832,  "trafficTrend": "rising"},
    {"locationId": "loc_residential_transit_hub","date": "2026-06-10", "hour": "08", "peakHours": ["07","08","17","18"], "estimatedPedestrians": 540,  "trafficTrend": "stable"},

    {"locationId": "loc_downtown_high_street",   "date": "2026-06-11", "hour": "12", "peakHours": ["12","13","18","19"], "estimatedPedestrians": 880,  "trafficTrend": "rising"},
    {"locationId": "loc_downtown_high_street",   "date": "2026-06-11", "hour": "18", "peakHours": ["12","13","18","19"], "estimatedPedestrians": 982,  "trafficTrend": "peak"},
    {"locationId": "loc_university_square",      "date": "2026-06-11", "hour": "14", "peakHours": ["11","12","14","15","18","19"], "estimatedPedestrians": 1082, "trafficTrend": "peak"},
    {"locationId": "loc_university_square",      "date": "2026-06-11", "hour": "19", "peakHours": ["11","12","14","15","18","19"], "estimatedPedestrians": 925,  "trafficTrend": "falling"},
    {"locationId": "loc_market_square",          "date": "2026-06-11", "hour": "10", "peakHours": ["10","11","16","17"], "estimatedPedestrians": 648,  "trafficTrend": "stable"},
    {"locationId": "loc_central_park",           "date": "2026-06-11", "hour": "15", "peakHours": ["15","16","17","18"], "estimatedPedestrians": 604,  "trafficTrend": "rising"},
    {"locationId": "loc_beach_area",             "date": "2026-06-11", "hour": "17", "peakHours": ["17","18","19","20"], "estimatedPedestrians": 710,  "trafficTrend": "rising"},
    {"locationId": "loc_residential_transit_hub","date": "2026-06-11", "hour": "08", "peakHours": ["07","08","17","18"], "estimatedPedestrians": 455,  "trafficTrend": "stable"},

    {"locationId": "loc_downtown_high_street",   "date": "2026-06-12", "hour": "12", "peakHours": ["12","13","18","19"], "estimatedPedestrians": 1020, "trafficTrend": "rising"},
    {"locationId": "loc_downtown_high_street",   "date": "2026-06-12", "hour": "18", "peakHours": ["12","13","18","19"], "estimatedPedestrians": 1140, "trafficTrend": "peak"},
    {"locationId": "loc_university_square",      "date": "2026-06-12", "hour": "14", "peakHours": ["11","12","14","15","18","19"], "estimatedPedestrians": 1255, "trafficTrend": "peak"},
    {"locationId": "loc_university_square",      "date": "2026-06-12", "hour": "19", "peakHours": ["11","12","14","15","18","19"], "estimatedPedestrians": 1073, "trafficTrend": "falling"},
    {"locationId": "loc_market_square",          "date": "2026-06-12", "hour": "10", "peakHours": ["10","11","16","17"], "estimatedPedestrians": 743,  "trafficTrend": "stable"},
    {"locationId": "loc_market_square",          "date": "2026-06-12", "hour": "16", "peakHours": ["10","11","16","17"], "estimatedPedestrians": 960,  "trafficTrend": "rising"},
    {"locationId": "loc_central_park",           "date": "2026-06-12", "hour": "15", "peakHours": ["15","16","17","18"], "estimatedPedestrians": 693,  "trafficTrend": "rising"},
    {"locationId": "loc_beach_area",             "date": "2026-06-12", "hour": "17", "peakHours": ["17","18","19","20"], "estimatedPedestrians": 814,  "trafficTrend": "rising"},
    {"locationId": "loc_residential_transit_hub","date": "2026-06-12", "hour": "08", "peakHours": ["07","08","17","18"], "estimatedPedestrians": 528,  "trafficTrend": "stable"}
  ]
}
